dapper_sqls/__init__.py
dapper_sqls/_types.py
dapper_sqls/config.py
dapper_sqls/decorators.py
dapper_sqls/utils.py
dapper_sqls/async_dapper/__init__.py
dapper_sqls/async_dapper/async_dapper.py
dapper_sqls/async_dapper/async_executors.py
dapper_sqls/builders/__init__.py
dapper_sqls/builders/query.py
dapper_sqls/builders/stored.py
dapper_sqls/builders/stp.py
dapper_sqls/builders/model/__init__.py
dapper_sqls/builders/model/model.py
dapper_sqls/builders/model/utils.py
dapper_sqls/dapper/__init__.py
dapper_sqls/dapper/dapper.py
dapper_sqls/dapper/executors.py
dapper_sqls/http/__init__.py
dapper_sqls/http/aiohttp.py
dapper_sqls/http/decorators.py
dapper_sqls/http/models.py
dapper_sqls/http/request.py
dapper_sqls/models/__init__.py
dapper_sqls/models/base.py
dapper_sqls/models/connection.py
dapper_sqls/models/http.py
dapper_sqls/models/query_field.py
dapper_sqls/models/result.py
dapper_sqls/sqlite/__init__.py
dapper_sqls/sqlite/async_local_database.py
dapper_sqls/sqlite/decorators.py
dapper_sqls/sqlite/installer.py
dapper_sqls/sqlite/local_database.py
dapper_sqls/sqlite/models.py
dapper_sqls/sqlite/utils.py
dapper_sqls-1.2.4.dist-info/METADATA
dapper_sqls-1.2.4.dist-info/WHEEL
dapper_sqls-1.2.4.dist-info/top_level.txt
dapper_sqls-1.2.4.dist-info/RECORD
