Metadata-Version: 2.1
Name: dapper-sqls
Version: 1.2.4
Summary: UNKNOWN
Home-page: UNKNOWN
Author: Samuel Semedo
License: UNKNOWN
Platform: UNKNOWN
Requires-Dist: aiohappyeyeballs
Requires-Dist: aiohttp
Requires-Dist: aioodbc
Requires-Dist: aiosignal
Requires-Dist: aiosqlite
Requires-Dist: annotated-types
Requires-Dist: async-timeout
Requires-Dist: attrs
Requires-Dist: certifi
Requires-Dist: charset-normalizer
Requires-Dist: check-wheel-contents
Requires-Dist: click
Requires-Dist: colorama
Requires-Dist: frozenlist
Requires-Dist: greenlet
Requires-Dist: idna
Requires-Dist: multidict
Requires-Dist: packaging
Requires-Dist: propcache
Requires-Dist: pydantic
Requires-Dist: pydantic-core
Requires-Dist: PyJWT
Requires-Dist: pyodbc
Requires-Dist: requests
Requires-Dist: SQLAlchemy
Requires-Dist: tomli
Requires-Dist: typing-extensions
Requires-Dist: urllib3
Requires-Dist: wheel-filename
Requires-Dist: yarl
Requires-Dist: sqlparse
